dojo_toolkit/__init__.py
dojo_toolkit/assets/g.jpg
dojo_toolkit/assets/r.jpg
dojo_toolkit/assets/sounds/pass.wav
dojo_toolkit/assets/sounds/start.wav
dojo_toolkit/assets/sounds/timeup.wav
dojo_toolkit/code_handler.py
dojo_toolkit/dojo.py
dojo_toolkit/dojo_thread.py
dojo_toolkit/main.py
dojo_toolkit/notifier.py
dojo_toolkit/settings.py
dojo_toolkit/sound_handler.py
dojo_toolkit/test_runner.py
dojo_toolkit/timer.py
dojo_toolkit-0.8.1.dist-info/LICENSE
dojo_toolkit-0.8.1.dist-info/METADATA
dojo_toolkit-0.8.1.dist-info/WHEEL
dojo_toolkit-0.8.1.dist-info/entry_points.txt
dojo_toolkit-0.8.1.dist-info/RECORD
